BitSightAPI/__init__.py
BitSightAPI/alerts.py
BitSightAPI/client.py
BitSightAPI/companies.py
BitSightAPI/company_relationships.py
BitSightAPI/company_requests.py
BitSightAPI/customers.py
BitSightAPI/findings.py
BitSightAPI/folders.py
BitSightAPI/industries.py
BitSightAPI/insights.py
BitSightAPI/news.py
BitSightAPI/portfolio.py
BitSightAPI/products.py
BitSightAPI/rapid_underwriting_assessments.py
BitSightAPI/reports.py
BitSightAPI/subscriptions.py
BitSightAPI/tiers.py
BitSightAPI/users.py
BitSightAPI-1.0.2.dist-info/LICENSE
BitSightAPI-1.0.2.dist-info/METADATA
BitSightAPI-1.0.2.dist-info/WHEEL
BitSightAPI-1.0.2.dist-info/top_level.txt
BitSightAPI-1.0.2.dist-info/RECORD
