Metadata-Version: 2.1
Name: BitSightAPI
Version: 1.0.2
Summary: A Python wrapper for the BitSight API.
Home-page: https://github.com/infosecsapper/BitSightAPI
Author: InfosecSapper
Author-email: contact@infosecsapper.com
License: GPLv3
Platform: UNKNOWN
Classifier: Programming Language :: Python :: 3
Classifier: License :: OSI Approved :: GNU General Public License v3 (GPLv3)
Classifier: Operating System :: OS Independent
Classifier: Development Status :: 5 - Production/Stable
Classifier: Intended Audience :: Developers
Classifier: Topic :: Software Development :: Libraries :: Python Modules
Requires-Python: >=3.7
Requires-Dist: requests (>=2.22.0)
